dj_fast/__init__.py
dj_fast/__main__.py
dj_fast/cli.py
dj_fast-0.1.3.dist-info/LICENSE
dj_fast-0.1.3.dist-info/METADATA
dj_fast-0.1.3.dist-info/WHEEL
dj_fast-0.1.3.dist-info/entry_points.txt
dj_fast-0.1.3.dist-info/top_level.txt
dj_fast-0.1.3.dist-info/RECORD
