Metadata-Version: 2.1
Name: dj-fast
Version: 0.1.3
Summary: A fast and easy Django project setup tool.
Home-page: https://github.com/yourusername/dj-fast
Author: Sander Hegeman
Author-email: me@heysander.com
Classifier: Programming Language :: Python :: 3
Classifier: Framework :: Django
Classifier: License :: OSI Approved :: MIT License
Classifier: Operating System :: OS Independent
Requires-Python: >=3.6
License-File: LICENSE
Requires-Dist: click
Requires-Dist: django
Requires-Dist: inquirer
Requires-Dist: pytz
Requires-Dist: python-dotenv
